posteriordb/__init__.py
posteriordb/dataset.py
posteriordb/model.py
posteriordb/model_implementation_base.py
posteriordb/posterior.py
posteriordb/posterior_database.py
posteriordb/posterior_database_github.py
posteriordb/pymc3_model_implementation.py
posteriordb/stan_model_implementation.py
posteriordb/util.py
posteriordb-0.2.0.dist-info/LICENSE
posteriordb-0.2.0.dist-info/METADATA
posteriordb-0.2.0.dist-info/WHEEL
posteriordb-0.2.0.dist-info/top_level.txt
posteriordb-0.2.0.dist-info/RECORD
