Metadata-Version: 2.1
Name: posteriordb
Version: 0.2.0
Summary: python interface to posterior database
Home-page: https://github.com/MansMeg/posteriordb
Author: Eero Linna
Author-email: eero.linna@aalto.fi
License: GPL
Platform: UNKNOWN
Requires-Dist: requests
